{"item":[{"id":"22b34faa-b019-482f-9033-908aea4664ed","name":"Create a new todo","request":{"name":"Create a new todo","description":{"content":"Create a new todo","type":"text/plain"},"url":{"path":["todos","create"],"host":["{{baseUrl}}"],"query":[],"variable":[]},"header":[{"key":"Content-Type","value":"application/json"},{"key":"Accept","value":"application/json"}],"method":"POST","auth":null,"body":{"mode":"raw","raw":"{\n  \"description\": \"<string>\",\n  \"title\": \"<string>\"\n}","options":{"raw":{"language":"json"}}}},"response":[{"id":"57a88abb-2540-476a-ada1-c48e7e81a03d","name":"Create a new todo successfully","originalRequest":{"url":{"path":["todos","create"],"host":["{{baseUrl}}"],"query":[],"variable":[]},"method":"POST","body":{"mode":"raw","raw":"{\n  \"description\": \"Buy milk from the store\",\n  \"title\": \"Buy milk\"\n}","options":{"raw":{"language":"json"}}}},"status":"OK","code":200,"header":[{"key":"Content-Type","value":"application/json"}],"body":"{\n  \"code\": 200,\n  \"success\": true,\n  \"message\": \"Todo successfully created.\"\n}","cookie":[],"_postman_previewlanguage":"json"},{"id":"3abb1a2f-3869-4bb4-926c-1cfe5af7ee31","name":"Validation error","originalRequest":{"url":{"path":["todos","create"],"host":["{{baseUrl}}"],"query":[],"variable":[]},"method":"POST","body":{"mode":"raw","raw":"{\n  \"description\": \"Buy milk from the store\",\n  \"title\": \"Buy milk\"\n}","options":{"raw":{"language":"json"}}}},"status":"Bad Request","code":400,"header":[{"key":"Content-Type","value":"application/json"}],"body":"{\n  \"code\": 400,\n  \"success\": false,\n  \"message\": \"Validation failed\",\n  \"errors\": [\n    {\n      \"name\": \"ValidationError\",\n      \"type\": \"required\",\n      \"message\": \"The property is required\",\n      \"expected\": \"The expected value\",\n      \"actual\": \"The actual value\"\n    },\n    {\n      \"name\": \"ValidationError\",\n      \"type\": \"required\",\n      \"message\": \"The property is required\",\n      \"expected\": \"The expected value\",\n      \"actual\": \"The actual value\"\n    }\n  ]\n}","cookie":[],"_postman_previewlanguage":"json"}],"event":[],"protocolProfileBehavior":{"disableBodyPruning":true}}],"event":[],"variable":[{"type":"string","value":"http://localhost:3000","key":"baseUrl"}],"info":{"_postman_id":"815a3a8d-3adb-4cdb-a23f-e00eabe4e4f5","name":"Todo API","schema":"https://schema.getpostman.com/json/collection/v2.1.0/collection.json","description":{"content":"Todo API","type":"text/plain"}}}